{
"type": "FeatureCollection",
"name": "bati_beaulieu_V2_regroup_zone_V2_centro",
"crs": { "type": "name", "properties": { "name": "urn:ogc:def:crs:OGC:1.3:CRS84" } },
"features": [
{ "type": "Feature", "properties": { "zone": "Campus de Beaulieu" }, "geometry": { "type": "Point", "coordinates": [ -1.639361271498451, 48.117552253927713 ] } },
{ "type": "Feature", "properties": { "zone": "ENSCR" }, "geometry": { "type": "Point", "coordinates": [ -1.633368439634685, 48.117980455424629 ] } },
{ "type": "Feature", "properties": { "zone": "INSA" }, "geometry": { "type": "Point", "coordinates": [ -1.634835037067774, 48.121735298761024 ] } },
{ "type": "Feature", "properties": { "zone": "IUT Clos Courtel" }, "geometry": { "type": "Point", "coordinates": [ -1.630790783569432, 48.123197282514489 ] } },
{ "type": "Feature", "properties": { "zone": "Résidences CROUS" }, "geometry": { "type": "Point", "coordinates": [ -1.64335068300934, 48.1231651753981 ] } }
]
}
